CHANGES.rst
CONTRIBUTORS.rst
MANIFEST.in
README.rst
base.cfg
bootstrap.py
buildout.cfg
constraints.txt
constraints_plone52.txt
constraints_plone60.txt
requirements.txt
requirements_plone52.txt
requirements_plone60.txt
setup.py
test_plone52.cfg
test_plone60.cfg
docs/INSTALL.txt
docs/LICENSE.EUPL
docs/LICENSE.GPL
docs/LICENSE.txt
src/slc/__init__.py
src/slc.xliff.egg-info/PKG-INFO
src/slc.xliff.egg-info/SOURCES.txt
src/slc.xliff.egg-info/dependency_links.txt
src/slc.xliff.egg-info/entry_points.txt
src/slc.xliff.egg-info/namespace_packages.txt
src/slc.xliff.egg-info/not-zip-safe
src/slc.xliff.egg-info/requires.txt
src/slc.xliff.egg-info/top_level.txt
src/slc/xliff/CHANGES.txt
src/slc/xliff/README.txt
src/slc/xliff/TODO.txt
src/slc/xliff/__init__.py
src/slc/xliff/configure.zcml
src/slc/xliff/interfaces.py
src/slc/xliff/refresh.txt
src/slc/xliff/testing.zcml
src/slc/xliff/tool.gif
src/slc/xliff/upgrades.py
src/slc/xliff/upgrades.zcml
src/slc/xliff/version.txt
src/slc/xliff/xliff.py
src/slc/xliff/adapters/__init__.py
src/slc/xliff/adapters/configure.zcml
src/slc/xliff/adapters/dx.py
src/slc/xliff/browser/__init__.py
src/slc/xliff/browser/configure.zcml
src/slc/xliff/browser/xliff_forms.py
src/slc/xliff/browser/templates/failure_icon.gif
src/slc/xliff/browser/templates/success_icon.gif
src/slc/xliff/browser/templates/xliff_icon.gif
src/slc/xliff/profiles/default/actions.xml
src/slc/xliff/profiles/default/browserlayer.xml
src/slc/xliff/profiles/default/metadata.xml
src/slc/xliff/profiles/testing/types.xml
src/slc/xliff/profiles/testing/types/test_content.xml
src/slc/xliff/profiles/uninstall/actions.xml
src/slc/xliff/profiles/uninstall/browserlayer.xml
src/slc/xliff/templates/__init__.py
src/slc/xliff/templates/html.py
src/slc/xliff/templates/html_attr_body.pt
src/slc/xliff/templates/html_file_body.pt
src/slc/xliff/templates/xliff.py
src/slc/xliff/templates/xliff_attr_body.pt
src/slc/xliff/templates/xliff_file_body.pt
src/slc/xliff/tests/__init__.py
src/slc/xliff/tests/base.py
src/slc/xliff/tests/content.py
src/slc/xliff/tests/test_setup.py
src/slc/xliff/tests/test_utils.py
src/slc/xliff/tests/test_xliff.py