Metadata-Version: 2.1
Name: slc.xliff
Version: 4.0
Summary: A framework to allow im and export of xliff files for translations
Home-page: https://github.com/collective/slc.xliff
Author: Syslab.com GmbH
Author-email: info@syslab.com
License: GPL + EUPL
Keywords: xliff translation import export
Platform: UNKNOWN
Classifier: Framework :: Plone
Classifier: Framework :: Plone :: 5.2
Classifier: Programming Language :: Python
Classifier: Programming Language :: Python :: 3.7
Classifier: Programming Language :: Python :: 3.8
Classifier: Topic :: Software Development :: Libraries :: Python Modules
Classifier: License :: OSI Approved :: GNU General Public License (GPL)
Classifier: License :: OSI Approved :: European Union Public Licence 1.1 (EUPL 1.1)
Provides-Extra: plone4
Provides-Extra: test
